[{"videoId":"26miDVwWORQ","image":"https://img.youtube.com/vi/26miDVwWORQ/0.jpg","title":"Lomba Cerdas Cermat Tingkat SMP Se-Kota Bekasi"},{"videoId":"mcYoeu_brJw","image":"https://img.youtube.com/vi/mcYoeu_brJw/0.jpg","title":"MUSRENBANG TINGKAT KECAMATAN DALAM RANGKA PENYUSUNAN RKPD KOTA BEKASI TAHUN 2023"},{"videoId":"hkC-1s8Q7mc","image":"https://img.youtube.com/vi/hkC-1s8Q7mc/0.jpg","title":"Peresmian Alun-Alun & BCCP Kota Bekasi"},{"videoId":"O8bI2mL4JkY","image":"https://img.youtube.com/vi/O8bI2mL4JkY/0.jpg","title":"Hari Peduli Sampah Nasional Kota Bekasi 2022"},{"videoId":"YPOcL0dEUcY","image":"https://img.youtube.com/vi/YPOcL0dEUcY/0.jpg","title":"SVP Innovation Fair 2022"},{"videoId":"HiEv6pUnEfI","image":"https://img.youtube.com/vi/HiEv6pUnEfI/0.jpg","title":"Rapat Koordinasi Penanganan dan Pengendalian Covid-19 di Kota Bekasi"},{"videoId":"ks5snBwNPf8","image":"https://img.youtube.com/vi/ks5snBwNPf8/0.jpg","title":"Deklarasi Komitmen Bersama Anti Korupsi Kecamatan Pondokgede"},{"videoId":"l3TXySgfmHA","image":"https://img.youtube.com/vi/l3TXySgfmHA/0.jpg","title":"Lomba Foto HUT Kota Bekasi Ke-25"},{"videoId":"MqbvR66InsY","image":"https://img.youtube.com/vi/MqbvR66InsY/0.jpg","title":"Deklarasi Komitmen Bersama Anti Korupsi Wilayah Kecamatan Jatiasih"},{"videoId":"0lcERadNir0","image":"https://img.youtube.com/vi/0lcERadNir0/0.jpg","title":"Pemkot Bekasi MoU dengan PT Goto Gojek Tokopedia"},{"videoId":"itp6NnBt_VA","image":"https://img.youtube.com/vi/itp6NnBt_VA/0.jpg","title":"Deklarasi Anti Korupsi Komitmen Bersama Medan Satria"},{"videoId":"Gx2GBTilhWU","image":"https://img.youtube.com/vi/Gx2GBTilhWU/0.jpg","title":"Deklarasi Anti Korupsi Komitmen Bersama Bekasi Selatan"},{"videoId":"so9n5lL_AdE","image":"https://img.youtube.com/vi/so9n5lL_AdE/0.jpg","title":"Sosialisasi dan Pembinaan penggunaan Aplikasi Otomasi Perpustakaan INLISLite"},{"videoId":"tdG-mjxCpz8","image":"https://img.youtube.com/vi/tdG-mjxCpz8/0.jpg","title":"Pemerintah Kota Bekasi Menandatangani Komitmen Bersama Tentang Anti Korupsi"},{"videoId":"i_MV7BpL758","image":"https://img.youtube.com/vi/i_MV7BpL758/0.jpg","title":"Ayoo Ikuti Lomba Logo HUT Kota Bekasi Ke 25"},{"videoId":"mQ16raUverY","image":"https://img.youtube.com/vi/mQ16raUverY/0.jpg","title":"Nilai Luhur dan Pengamalan Pancasila"},{"videoId":"ptjzrxSoGdQ","image":"https://img.youtube.com/vi/ptjzrxSoGdQ/0.jpg","title":"Kick Off MeetingPerencanaan Pembangunan Kota Bekasi Tahun 2023"},{"videoId":"x6NESPbkmp0","image":"https://img.youtube.com/vi/x6NESPbkmp0/0.jpg","title":"PERINGATI HARI IBU KE-93, PEREMPUAN BERDAYA INDONESIA MAJU"},{"videoId":"VD36ui82ypY","image":"https://img.youtube.com/vi/VD36ui82ypY/0.jpg","title":"Penyelanggaraan Vaksinasi Anak-Anak"},{"videoId":"RA4F5o0twpg","image":"https://img.youtube.com/vi/RA4F5o0twpg/0.jpg","title":"Anak Usia 6-11 Tahun di Bekasi Mulai Divaksin Covid-19"},{"videoId":"YnX7o7sve9g","image":"https://img.youtube.com/vi/YnX7o7sve9g/0.jpg","title":"Bekasi Smart City 2021"},{"videoId":"kzz4lkHtskc","image":"https://img.youtube.com/vi/kzz4lkHtskc/0.jpg","title":"DPPKB KOTA BEKASI UPPKA KOTA BEKASI"},{"videoId":"GWAwmO4mrqE","image":"https://img.youtube.com/vi/GWAwmO4mrqE/0.jpg","title":"Smart City Kota Bekasi"},{"videoId":"5xArs9Vp1zY","image":"https://img.youtube.com/vi/5xArs9Vp1zY/0.jpg","title":"Babak Kualifikasi Tenis Lapangan PORPROV XIV JAWA BARAT 2022 WILAYAH II"},{"videoId":"f4QEoYuXT0E","image":"https://img.youtube.com/vi/f4QEoYuXT0E/0.jpg","title":"Rabies Protectioan For Animal Health Practitioner"},{"videoId":"n-Bhrx1Uf-o","image":"https://img.youtube.com/vi/n-Bhrx1Uf-o/0.jpg","title":"Rabies Protectioan For Animal Health Practitioner"},{"videoId":"gL8tY7C3MrI","image":"https://img.youtube.com/vi/gL8tY7C3MrI/0.jpg","title":"Launching Club PCB Persipasi Kota Bekasi"},{"videoId":"BsqUoYqnYCI","image":"https://img.youtube.com/vi/BsqUoYqnYCI/0.jpg","title":"Selamat Hari Pahlawan 2021"},{"videoId":"QUbKQ8YLMPQ","image":"https://img.youtube.com/vi/QUbKQ8YLMPQ/0.jpg","title":"Sosialisasi Pelaksanaan Sertifikat Elektronik"},{"videoId":"L9K26TvDoGc","image":"https://img.youtube.com/vi/L9K26TvDoGc/0.jpg","title":"Seleksi Terbuka Calon Pejabat Pimpinan Tinggi Pratama"}]
